twint/__init__.py
twint/__version__.py
twint/config.py
twint/datelock.py
twint/db.py
twint/debug.py
twint/elasticsearch.py
twint/favorites.py
twint/feed.py
twint/followers.py
twint/following.py
twint/get.py
twint/output.py
twint/profile.py
twint/search.py
twint/tweet.py
twinter-1.1.2.2.dist-info/METADATA
twinter-1.1.2.2.dist-info/RECORD
twinter-1.1.2.2.dist-info/WHEEL
twinter-1.1.2.2.dist-info/top_level.txt
