Metadata-Version: 2.1
Name: twinter
Version: 1.1.2.2
Summary: An advanced Twitter scraping & OSINT tool.
Home-page: https://github.com/data-catalysis/twint
Author: Nguyen Cao
Author-email: ducnguyen@usedata.vn
License: MIT
Platform: UNKNOWN
Classifier: License :: OSI Approved :: MIT License
Classifier: Programming Language :: Python
Classifier: Programming Language :: Python :: 3
Classifier: Programming Language :: Python :: 3.5
Classifier: Programming Language :: Python :: 3.6
Requires-Python: >=3.5.0
Requires-Dist: aiohttp
Requires-Dist: aiodns
Requires-Dist: beautifulsoup4
Requires-Dist: cchardet
Requires-Dist: elasticsearch
